ja_complete/__init__.py
ja_complete/cli.py
ja_complete/completer.py
ja_complete/tokenizer.py
ja_complete/types.py
ja_complete/data/README.md
ja_complete/data/create_dummy_model.py
ja_complete/data/default_ngram.pkl
ja_complete/models/__init__.py
ja_complete/models/base.py
ja_complete/models/ngram.py
ja_complete/models/phrase.py
ja_complete/models/simple.py
ja_complete-0.1.0.dist-info/METADATA
ja_complete-0.1.0.dist-info/WHEEL
ja_complete-0.1.0.dist-info/entry_points.txt
ja_complete-0.1.0.dist-info/licenses/LICENSE
ja_complete-0.1.0.dist-info/licenses/LICENSE-CC-BY-SA.txt
ja_complete-0.1.0.dist-info/RECORD
