Metadata-Version: 2.4
Name: ja-complete
Version: 0.1.0
Summary: Lightweight offline Japanese input completion library
Project-URL: Homepage, https://github.com/Taketo-Yoda/ja-complete
Project-URL: Repository, https://github.com/Taketo-Yoda/ja-complete
Project-URL: Issues, https://github.com/Taketo-Yoda/ja-complete/issues
Author-email: Taketo Yoda <exhaust7.drs@gmail.com>
License: MIT
License-File: LICENSE
License-File: LICENSE-CC-BY-SA.txt
Keywords: completion,ime,input-method,japanese,nlp
Classifier: Development Status :: 3 - Alpha
Classifier: Intended Audience :: Developers
Classifier: License :: OSI Approved :: MIT License
Classifier: Programming Language :: Python :: 3
Classifier: Programming Language :: Python :: 3.10
Classifier: Programming Language :: Python :: 3.11
Classifier: Programming Language :: Python :: 3.12
Classifier: Topic :: Software Development :: Libraries :: Python Modules
Classifier: Topic :: Text Processing :: Linguistic
Requires-Python: >=3.10
Requires-Dist: janome>=0.5.0
Requires-Dist: pydantic>=2.12.5
